xnatuploader/__init__.py
xnatuploader/dicoms.py
xnatuploader/matcher.py
xnatuploader/put.py
xnatuploader/upload.py
xnatuploader/workbook.py
xnatuploader/xnatuploader.py
xnatuploader-1.1.1.dist-info/METADATA
xnatuploader-1.1.1.dist-info/WHEEL
xnatuploader-1.1.1.dist-info/entry_points.txt
xnatuploader-1.1.1.dist-info/top_level.txt
xnatuploader-1.1.1.dist-info/RECORD
