Metadata-Version: 2.1
Name: xnatuploader
Version: 1.1.1
Summary: CLI tool for uploading multiple files to XNAT
Home-page: https://github.com/SydneyInformaticsHub/xnatuploader
Author: Mike Lynch
Author-email: m.lynch@sydney.edu.au
Project-URL: Bug Tracker, https://github.com/SydneyInformaticsHub/xnatuploader/issues
Classifier: Programming Language :: Python :: 3
Classifier: License :: OSI Approved :: MIT License
Classifier: Operating System :: OS Independent
Classifier: Development Status :: 4 - Beta
Requires-Dist: xnatutils
Requires-Dist: xnat (==0.4.3)
Requires-Dist: openpyxl (>=3.0.10)
Requires-Dist: pydicom (>=2.3.0)
Requires-Dist: tqdm
Requires-Dist: click
Provides-Extra: test
Requires-Dist: pytest ; extra == 'test'
Requires-Dist: xnat4tests (>=0.3.2) ; extra == 'test'
